microgear/__init__.py
microgear/cache.py
microgear/client.py
microgear-1.2.6.dist-info/DESCRIPTION.rst
microgear-1.2.6.dist-info/METADATA
microgear-1.2.6.dist-info/RECORD
microgear-1.2.6.dist-info/WHEEL
microgear-1.2.6.dist-info/metadata.json
microgear-1.2.6.dist-info/top_level.txt
