Metadata-Version: 2.0
Name: microgear
Version: 1.2.6
Summary: Client library of Python, connect application code or hardware to netpie platform.
Home-page: https://github.com/netpieio/microgear-python
Author: netpie
Author-email: support@netpie.io
License: UNKNOWN
Keywords: netpie,iot,mqtt
Platform: UNKNOWN
Requires-Dist: certifi
Requires-Dist: paho-mqtt (==1.2.3)
Requires-Dist: requests
